MANIFEST.in
pyproject.toml
setup.cfg
setup.py
dummy_localstack_ext.egg-info/PKG-INFO
dummy_localstack_ext.egg-info/SOURCES.txt
dummy_localstack_ext.egg-info/dependency_links.txt
dummy_localstack_ext.egg-info/entry_points.txt
dummy_localstack_ext.egg-info/not-zip-safe
dummy_localstack_ext.egg-info/plux.json
dummy_localstack_ext.egg-info/requires.txt
dummy_localstack_ext.egg-info/top_level.txt
localstack_ext/__init__.py
localstack_ext/config.py
localstack_ext/constants.py
localstack_ext/plugins.py
localstack_ext/providers.py
localstack_ext/aws/__init__.py
localstack_ext/aws/api/__init__.py
localstack_ext/aws/api/amplify/__init__.py
localstack_ext/aws/api/apigatewaymanagementapi/__init__.py
localstack_ext/aws/api/apigatewayv2/__init__.py
localstack_ext/aws/api/appconfig/__init__.py
localstack_ext/aws/api/application_autoscaling/__init__.py
localstack_ext/aws/api/appsync/__init__.py
localstack_ext/aws/api/athena/__init__.py
localstack_ext/aws/api/autoscaling/__init__.py
localstack_ext/aws/api/backup/__init__.py
localstack_ext/aws/api/batch/__init__.py
localstack_ext/aws/api/ce/__init__.py
localstack_ext/aws/api/cloudfront/__init__.py
localstack_ext/aws/api/cloudtrail/__init__.py
localstack_ext/aws/api/codecommit/__init__.py
localstack_ext/aws/api/cognito_identity/__init__.py
localstack_ext/aws/api/cognito_idp/__init__.py
localstack_ext/aws/api/ecr/__init__.py
localstack_ext/aws/api/ecs/__init__.py
localstack_ext/aws/api/efs/__init__.py
localstack_ext/aws/api/eks/__init__.py
localstack_ext/aws/api/elasticache/__init__.py
localstack_ext/aws/api/elasticbeanstalk/__init__.py
localstack_ext/aws/api/elb/__init__.py
localstack_ext/aws/api/elbv2/__init__.py
localstack_ext/aws/api/emr/__init__.py
localstack_ext/aws/api/glacier/__init__.py
localstack_ext/aws/api/glue/__init__.py
localstack_ext/aws/api/iot/__init__.py
localstack_ext/aws/api/iot_data/__init__.py
localstack_ext/aws/api/iotanalytics/__init__.py
localstack_ext/aws/api/iotwireless/__init__.py
localstack_ext/aws/api/kafka/__init__.py
localstack_ext/aws/api/lakeformation/__init__.py
localstack_ext/aws/api/mediastore/__init__.py
localstack_ext/aws/api/mediastore_data/__init__.py
localstack_ext/aws/api/mwaa/__init__.py
localstack_ext/aws/api/organizations/__init__.py
localstack_ext/aws/api/qldb/__init__.py
localstack_ext/aws/api/qldb_session/__init__.py
